<annotation>
	<folder>images</folder>
	<filename>India_004730.jpg</filename>
	<size>
		<width>720</width>
		<height>720</height>
		<depth>3</depth>
	</size>
	<segmented>0</segmented>
	<object>
		<name>D20</name>
		<pose>Unspecified</pose>
		<truncated>0</truncated>
		<difficult>0</difficult>
		<bndbox>
			<xmin>286</xmin>
			<ymin>528</ymin>
			<xmax>424</xmax>
			<ymax>686</ymax>
		</bndbox>
	</object>
	<object>
		<name>D00</name>
		<pose>Unspecified</pose>
		<truncated>0</truncated>
		<difficult>0</difficult>
		<bndbox>
			<xmin>405</xmin>
			<ymin>547</ymin>
			<xmax>489</xmax>
			<ymax>687</ymax>
		</bndbox>
	</object>
	<object>
		<name>D10</name>
		<pose>Unspecified</pose>
		<truncated>0</truncated>
		<difficult>0</difficult>
		<bndbox>
			<xmin>283</xmin>
			<ymin>541</ymin>
			<xmax>414</xmax>
			<ymax>565</ymax>
		</bndbox>
	</object>
</annotation>