<annotation>
	<folder>images</folder>
	<filename>India_005320.jpg</filename>
	<size>
		<width>720</width>
		<height>720</height>
		<depth>3</depth>
	</size>
	<segmented>0</segmented>
	<object>
		<name>D00</name>
		<pose>Unspecified</pose>
		<truncated>0</truncated>
		<difficult>0</difficult>
		<bndbox>
			<xmin>404</xmin>
			<ymin>648</ymin>
			<xmax>482</xmax>
			<ymax>719</ymax>
		</bndbox>
	</object>
	<object>
		<name>D00</name>
		<pose>Unspecified</pose>
		<truncated>0</truncated>
		<difficult>0</difficult>
		<bndbox>
			<xmin>128</xmin>
			<ymin>554</ymin>
			<xmax>234</xmax>
			<ymax>663</ymax>
		</bndbox>
	</object>
	<object>
		<name>D00</name>
		<pose>Unspecified</pose>
		<truncated>0</truncated>
		<difficult>0</difficult>
		<bndbox>
			<xmin>235</xmin>
			<ymin>472</ymin>
			<xmax>293</xmax>
			<ymax>547</ymax>
		</bndbox>
	</object>
</annotation>