<annotation>
	<folder>images</folder>
	<filename>India_001246.jpg</filename>
	<size>
		<width>720</width>
		<height>720</height>
		<depth>3</depth>
	</size>
	<segmented>0</segmented>
	<object>
		<name>D20</name>
		<pose>Unspecified</pose>
		<truncated>0</truncated>
		<difficult>0</difficult>
		<bndbox>
			<xmin>84</xmin>
			<ymin>494</ymin>
			<xmax>600</xmax>
			<ymax>715</ymax>
		</bndbox>
	</object>
	<object>
		<name>D40</name>
		<pose>Unspecified</pose>
		<truncated>0</truncated>
		<difficult>0</difficult>
		<bndbox>
			<xmin>194</xmin>
			<ymin>562</ymin>
			<xmax>451</xmax>
			<ymax>713</ymax>
		</bndbox>
	</object>
</annotation>