<annotation>
	<folder>images</folder>
	<filename>India_004639.jpg</filename>
	<size>
		<width>720</width>
		<height>720</height>
		<depth>3</depth>
	</size>
	<segmented>0</segmented>
	<object>
		<name>D40</name>
		<pose>Unspecified</pose>
		<truncated>0</truncated>
		<difficult>0</difficult>
		<bndbox>
			<xmin>573</xmin>
			<ymin>500</ymin>
			<xmax>687</xmax>
			<ymax>628</ymax>
		</bndbox>
	</object>
	<object>
		<name>D40</name>
		<pose>Unspecified</pose>
		<truncated>0</truncated>
		<difficult>0</difficult>
		<bndbox>
			<xmin>525</xmin>
			<ymin>433</ymin>
			<xmax>606</xmax>
			<ymax>489</ymax>
		</bndbox>
	</object>
	<object>
		<name>D40</name>
		<pose>Unspecified</pose>
		<truncated>0</truncated>
		<difficult>0</difficult>
		<bndbox>
			<xmin>425</xmin>
			<ymin>408</ymin>
			<xmax>507</xmax>
			<ymax>457</ymax>
		</bndbox>
	</object>
	<object>
		<name>D40</name>
		<pose>Unspecified</pose>
		<truncated>0</truncated>
		<difficult>0</difficult>
		<bndbox>
			<xmin>259</xmin>
			<ymin>447</ymin>
			<xmax>433</xmax>
			<ymax>540</ymax>
		</bndbox>
	</object>
</annotation>