<annotation>
  <folder>images</folder>
  <filename>Czech_003413.jpg</filename>
  <size>
    <depth>3</depth>
    <width>600</width>
    <height>600</height>
  </size>
  <object>
    <name>D10</name>
    <bndbox>
      <xmin>4</xmin>
      <ymin>474</ymin>
      <xmax>309</xmax>
      <ymax>503</ymax>
    </bndbox>
  </object>
  <object>
    <name>D10</name>
    <bndbox>
      <xmin>119</xmin>
      <ymin>403</ymin>
      <xmax>304</xmax>
      <ymax>427</ymax>
    </bndbox>
  </object>
</annotation>