<annotation>
	<folder>images</folder>
	<filename>Japan_007684.jpg</filename>
	<size>
		<width>600</width>
		<height>600</height>
		<depth>3</depth>
	</size>
	<segmented>0</segmented>
	<object>
		<name>D20</name>
		<pose>Unspecified</pose>
		<truncated>1</truncated>
		<difficult>0</difficult>
		<bndbox>
			<xmin>344</xmin>
			<ymin>368</ymin>
			<xmax>548</xmax>
			<ymax>600</ymax>
		</bndbox>
	</object>
	<object>
		<name>D10</name>
		<pose>Unspecified</pose>
		<truncated>0</truncated>
		<difficult>0</difficult>
		<bndbox>
			<xmin>303</xmin>
			<ymin>578</ymin>
			<xmax>429</xmax>
			<ymax>593</ymax>
		</bndbox>
	</object>
	<object>
		<name>D10</name>
		<pose>Unspecified</pose>
		<truncated>0</truncated>
		<difficult>0</difficult>
		<bndbox>
			<xmin>178</xmin>
			<ymin>492</ymin>
			<xmax>285</xmax>
			<ymax>514</ymax>
		</bndbox>
	</object>
</annotation>