<annotation>
	<folder>images</folder>
	<filename>Japan_005136.jpg</filename>
	<size>
		<width>600</width>
		<height>600</height>
		<depth>3</depth>
	</size>
	<segmented>0</segmented>
	<object>
		<name>D20</name>
		<pose>Unspecified</pose>
		<truncated>0</truncated>
		<difficult>0</difficult>
		<bndbox>
			<xmin>166</xmin>
			<ymin>421</ymin>
			<xmax>245</xmax>
			<ymax>579</ymax>
		</bndbox>
	</object>
	<object>
		<name>D10</name>
		<pose>Unspecified</pose>
		<truncated>0</truncated>
		<difficult>0</difficult>
		<bndbox>
			<xmin>264</xmin>
			<ymin>417</ymin>
			<xmax>488</xmax>
			<ymax>450</ymax>
		</bndbox>
	</object>
	<object>
		<name>D10</name>
		<pose>Unspecified</pose>
		<truncated>0</truncated>
		<difficult>0</difficult>
		<bndbox>
			<xmin>334</xmin>
			<ymin>371</ymin>
			<xmax>445</xmax>
			<ymax>389</ymax>
		</bndbox>
	</object>
</annotation>