<annotation>
	<folder>images</folder>
	<filename>Japan_002032.jpg</filename>
	<size>
		<width>600</width>
		<height>600</height>
		<depth>3</depth>
	</size>
	<segmented>0</segmented>
	<object>
		<name>D50</name>
		<pose>Unspecified</pose>
		<truncated>0</truncated>
		<difficult>0</difficult>
		<bndbox>
			<xmin>141</xmin>
			<ymin>168</ymin>
			<xmax>201</xmax>
			<ymax>185</ymax>
		</bndbox>
	</object>
	<object>
		<name>D50</name>
		<pose>Unspecified</pose>
		<truncated>0</truncated>
		<difficult>0</difficult>
		<bndbox>
			<xmin>340</xmin>
			<ymin>124</ymin>
			<xmax>382</xmax>
			<ymax>134</ymax>
		</bndbox>
	</object>
	<object>
		<name>D50</name>
		<pose>Unspecified</pose>
		<truncated>0</truncated>
		<difficult>0</difficult>
		<bndbox>
			<xmin>490</xmin>
			<ymin>117</ymin>
			<xmax>536</xmax>
			<ymax>128</ymax>
		</bndbox>
	</object>
	<object>
		<name>D10</name>
		<pose>Unspecified</pose>
		<truncated>0</truncated>
		<difficult>0</difficult>
		<bndbox>
			<xmin>113</xmin>
			<ymin>258</ymin>
			<xmax>452</xmax>
			<ymax>279</ymax>
		</bndbox>
	</object>
	<object>
		<name>D20</name>
		<pose>Unspecified</pose>
		<truncated>0</truncated>
		<difficult>0</difficult>
		<bndbox>
			<xmin>407</xmin>
			<ymin>182</ymin>
			<xmax>500</xmax>
			<ymax>298</ymax>
		</bndbox>
	</object>
</annotation>