<annotation>
	<folder>images</folder>
	<filename>Japan_003515.jpg</filename>
	<size>
		<width>600</width>
		<height>600</height>
		<depth>3</depth>
	</size>
	<segmented>0</segmented>
	<object>
		<name>D43</name>
		<pose>Unspecified</pose>
		<truncated>0</truncated>
		<difficult>0</difficult>
		<bndbox>
			<xmin>4</xmin>
			<ymin>430</ymin>
			<xmax>597</xmax>
			<ymax>594</ymax>
		</bndbox>
	</object>
	<object>
		<name>D20</name>
		<pose>Unspecified</pose>
		<truncated>0</truncated>
		<difficult>0</difficult>
		<bndbox>
			<xmin>298</xmin>
			<ymin>368</ymin>
			<xmax>363</xmax>
			<ymax>413</ymax>
		</bndbox>
	</object>
	<object>
		<name>D50</name>
		<pose>Unspecified</pose>
		<truncated>0</truncated>
		<difficult>0</difficult>
		<bndbox>
			<xmin>342</xmin>
			<ymin>364</ymin>
			<xmax>382</xmax>
			<ymax>377</ymax>
		</bndbox>
	</object>
	<object>
		<name>D50</name>
		<pose>Unspecified</pose>
		<truncated>0</truncated>
		<difficult>0</difficult>
		<bndbox>
			<xmin>328</xmin>
			<ymin>348</ymin>
			<xmax>385</xmax>
			<ymax>364</ymax>
		</bndbox>
	</object>
</annotation>