<annotation>
	<folder>images</folder>
	<filename>Japan_009922.jpg</filename>
	<size>
		<width>600</width>
		<height>600</height>
		<depth>3</depth>
	</size>
	<segmented>0</segmented>
	<object>
		<name>D20</name>
		<pose>Unspecified</pose>
		<truncated>0</truncated>
		<difficult>0</difficult>
		<bndbox>
			<xmin>5</xmin>
			<ymin>539</ymin>
			<xmax>444</xmax>
			<ymax>598</ymax>
		</bndbox>
	</object>
	<object>
		<name>D20</name>
		<pose>Unspecified</pose>
		<truncated>0</truncated>
		<difficult>0</difficult>
		<bndbox>
			<xmin>247</xmin>
			<ymin>393</ymin>
			<xmax>317</xmax>
			<ymax>456</ymax>
		</bndbox>
	</object>
	<object>
		<name>D20</name>
		<pose>Unspecified</pose>
		<truncated>0</truncated>
		<difficult>0</difficult>
		<bndbox>
			<xmin>13</xmin>
			<ymin>447</ymin>
			<xmax>131</xmax>
			<ymax>538</ymax>
		</bndbox>
	</object>
	<object>
		<name>D20</name>
		<pose>Unspecified</pose>
		<truncated>0</truncated>
		<difficult>0</difficult>
		<bndbox>
			<xmin>190</xmin>
			<ymin>459</ymin>
			<xmax>328</xmax>
			<ymax>519</ymax>
		</bndbox>
	</object>
	<object>
		<name>D20</name>
		<pose>Unspecified</pose>
		<truncated>0</truncated>
		<difficult>0</difficult>
		<bndbox>
			<xmin>105</xmin>
			<ymin>369</ymin>
			<xmax>188</xmax>
			<ymax>435</ymax>
		</bndbox>
	</object>
</annotation>