<annotation>
	<folder>images</folder>
	<filename>Japan_000877.jpg</filename>
	<size>
		<width>600</width>
		<height>600</height>
		<depth>3</depth>
	</size>
	<segmented>0</segmented>
	<object>
		<name>D10</name>
		<pose>Unspecified</pose>
		<truncated>0</truncated>
		<difficult>0</difficult>
		<bndbox>
			<xmin>33</xmin>
			<ymin>266</ymin>
			<xmax>439</xmax>
			<ymax>317</ymax>
		</bndbox>
	</object>
	<object>
		<name>D20</name>
		<pose>Unspecified</pose>
		<truncated>0</truncated>
		<difficult>0</difficult>
		<bndbox>
			<xmin>311</xmin>
			<ymin>252</ymin>
			<xmax>420</xmax>
			<ymax>361</ymax>
		</bndbox>
	</object>
</annotation>